{"nm":"_calendar","ddd":0,"h":144,"w":144,"meta":{"g":"@lottiefiles/toolkit-js 0.71.10","tc":"#eaedfe"},"layers":[{"ty":4,"nm":"V","sr":1,"st":0,"op":125,"ip":0,"ln":"1642","hasMask":false,"ao":0,"ks":{"a":{"a":0,"k":[0,0]},"s":{"a":0,"k":[100,100]},"p":{"a":0,"k":[0,0]},"r":{"a":0,"k":-90},"sa":{"a":0,"k":0},"o":{"a":0,"k":100}},"shapes":[{"ty":"gr","nm":"Partners","it":[{"ty":"sh","nm":"Path 1","d":1,"ks":{"a":0,"k":{"c":false,"i":[[0,0],[0,0],[0,0]],"o":[[0,0],[0,0],[0,0]],"v":[[-10.16,0],[-4.622,6.671],[10.16,-6.671]]}}},{"ty":"st","nm":"Stroke 1","lc":1,"lj":2,"ml":4,"o":{"a":0,"k":100},"w":{"a":0,"k":4},"c":{"a":0,"k":[1,1,1]}},{"ty":"tr","a":{"a":0,"k":[0,0]},"s":{"a":0,"k":[100,100]},"p":{"a":0,"k":[0,0]},"r":{"a":0,"k":0},"sa":{"a":0,"k":0},"o":{"a":0,"k":100}}]},{"ty":"tm","nm":"Trim Paths 1","e":{"a":1,"k":[{"o":{"x":0.5,"y":0},"i":{"x":0,"y":1},"s":[0],"t":0},{"o":{"x":0.5,"y":0},"i":{"x":0,"y":1},"s":[100],"t":25},{"o":{"x":0.5,"y":0},"i":{"x":0.833,"y":1},"s":[100],"t":114.999},{"o":{"x":0.167,"y":0},"i":{"x":0.833,"y":1},"s":[0],"t":115.999},{"s":[100],"t":124.999}]},"o":{"a":0,"k":0},"s":{"a":1,"k":[{"o":{"x":0.5,"y":0},"i":{"x":0.833,"y":1},"s":[0],"t":114.999},{"o":{"x":0.167,"y":0},"i":{"x":0.833,"y":1},"s":[100],"t":115.999},{"s":[100],"t":124.999}]},"m":1}],"ind":1,"parent":2},{"ty":4,"nm":"O","sr":1,"st":0,"op":125,"ip":0,"ln":"1641","hasMask":false,"ao":0,"ks":{"a":{"a":0,"k":[0,0]},"s":{"a":1,"k":[{"o":{"x":0.167,"y":0.167},"i":{"x":0.833,"y":0.833},"s":[100,100],"t":45},{"o":{"x":0.167,"y":0.167},"i":{"x":0.833,"y":0.833},"s":[102.647,102.647],"t":66.332},{"o":{"x":0.167,"y":0.167},"i":{"x":0.833,"y":0.833},"s":[95,95],"t":87.666},{"s":[100,100],"t":108.999}]},"p":{"a":1,"k":[{"o":{"x":0.307,"y":0},"i":{"x":0,"y":1},"s":[-42.75,-42.75],"t":10},{"o":{"x":1,"y":0},"i":{"x":0.728,"y":1},"s":[-42.75,-48.906],"t":25},{"s":[-42.75,-42.75],"t":45}]},"r":{"a":0,"k":90},"sa":{"a":0,"k":0},"o":{"a":0,"k":100}},"shapes":[{"ty":"gr","nm":"Partners","it":[{"ty":"el","nm":"Ellipse Path 1","d":1,"p":{"a":0,"k":[0,0]},"s":{"a":0,"k":[40.5,40.5]}},{"ty":"st","nm":"Stroke 1","lc":1,"lj":2,"ml":4,"o":{"a":0,"k":100},"w":{"a":0,"k":4},"c":{"a":0,"k":[0.4706,0.2863,1]}},{"ty":"fl","nm":"Fill 1","c":{"a":0,"k":[0.4706,0.2863,1]},"r":1,"o":{"a":0,"k":100}},{"ty":"tr","a":{"a":0,"k":[0,0]},"s":{"a":0,"k":[100,100]},"p":{"a":0,"k":[0,0]},"r":{"a":0,"k":0},"sa":{"a":0,"k":0},"o":{"a":0,"k":100}}]}],"ind":2,"parent":3},{"ty":4,"nm":"calendar","sr":1,"st":0,"op":125,"ip":0,"ln":"1639","hasMask":false,"ao":0,"ks":{"a":{"a":0,"k":[0,0]},"s":{"a":0,"k":[100,100]},"p":{"a":0,"k":[72,76.5]},"r":{"a":0,"k":0},"sa":{"a":0,"k":0},"o":{"a":0,"k":100}},"shapes":[{"ty":"gr","nm":"Group 1","it":[{"ty":"gr","nm":"Group 1","it":[{"ty":"sh","nm":"Path 1","d":1,"ks":{"a":0,"k":{"c":true,"i":[[0,0],[0,0],[0,0],[0,0]],"o":[[0,0],[0,0],[0,0],[0,0]],"v":[[6.375,-9.75],[-9.375,-9.75],[-6.375,9.75],[9.375,9.75]]}}},{"ty":"st","nm":"Stroke 1","lc":1,"lj":2,"ml":4,"o":{"a":0,"k":100},"w":{"a":0,"k":4.108},"c":{"a":0,"k":[0.1294,0.1294,0.1412]}},{"ty":"tr","a":{"a":0,"k":[0,0]},"s":{"a":0,"k":[100,100]},"p":{"a":0,"k":[37.125,24]},"r":{"a":0,"k":0},"sa":{"a":0,"k":0},"o":{"a":0,"k":100}}]},{"ty":"gr","nm":"Group 2","it":[{"ty":"sh","nm":"Path 1","d":1,"ks":{"a":0,"k":{"c":true,"i":[[0,0],[0,0],[0,0],[0,0]],"o":[[0,0],[0,0],[0,0],[0,0]],"v":[[6.375,-9.75],[-9.375,-9.75],[-6.375,9.75],[9.375,9.75]]}}},{"ty":"st","nm":"Stroke 1","lc":1,"lj":2,"ml":4,"o":{"a":0,"k":100},"w":{"a":0,"k":4.108},"c":{"a":0,"k":[0.1294,0.1294,0.1412]}},{"ty":"tr","a":{"a":0,"k":[0,0]},"s":{"a":0,"k":[100,100]},"p":{"a":0,"k":[21.375,24]},"r":{"a":0,"k":0},"sa":{"a":0,"k":0},"o":{"a":0,"k":100}}]},{"ty":"gr","nm":"Group 3","it":[{"ty":"sh","nm":"Path 1","d":1,"ks":{"a":0,"k":{"c":true,"i":[[0,0],[0,0],[0,0],[0,0]],"o":[[0,0],[0,0],[0,0],[0,0]],"v":[[6.375,-9.75],[-9.375,-9.75],[-6.375,9.75],[9.375,9.75]]}}},{"ty":"st","nm":"Stroke 1","lc":1,"lj":2,"ml":4,"o":{"a":0,"k":100},"w":{"a":0,"k":4.108},"c":{"a":0,"k":[0.1294,0.1294,0.1412]}},{"ty":"tr","a":{"a":0,"k":[0,0]},"s":{"a":0,"k":[100,100]},"p":{"a":0,"k":[5.625,24]},"r":{"a":0,"k":0},"sa":{"a":0,"k":0},"o":{"a":0,"k":100}}]},{"ty":"gr","nm":"Group 4","it":[{"ty":"sh","nm":"Path 1","d":1,"ks":{"a":0,"k":{"c":true,"i":[[0,0],[0,0],[0,0],[0,0]],"o":[[0,0],[0,0],[0,0],[0,0]],"v":[[6.375,-9.75],[-9.375,-9.75],[-6.375,9.75],[9.375,9.75]]}}},{"ty":"st","nm":"Stroke 1","lc":1,"lj":2,"ml":4,"o":{"a":0,"k":100},"w":{"a":0,"k":4.108},"c":{"a":0,"k":[0.1294,0.1294,0.1412]}},{"ty":"tr","a":{"a":0,"k":[0,0]},"s":{"a":0,"k":[100,100]},"p":{"a":0,"k":[-10.125,24]},"r":{"a":0,"k":0},"sa":{"a":0,"k":0},"o":{"a":0,"k":100}}]},{"ty":"gr","nm":"Group 5","it":[{"ty":"sh","nm":"Path 1","d":1,"ks":{"a":0,"k":{"c":true,"i":[[0,0],[0,0],[0,0],[0,0]],"o":[[0,0],[0,0],[0,0],[0,0]],"v":[[6.375,-9.75],[-9.375,-9.75],[-6.375,9.75],[9.375,9.75]]}}},{"ty":"st","nm":"Stroke 1","lc":1,"lj":2,"ml":4,"o":{"a":0,"k":100},"w":{"a":0,"k":4.108},"c":{"a":0,"k":[0.1294,0.1294,0.1412]}},{"ty":"tr","a":{"a":0,"k":[0,0]},"s":{"a":0,"k":[100,100]},"p":{"a":0,"k":[34.125,4.5]},"r":{"a":0,"k":0},"sa":{"a":0,"k":0},"o":{"a":0,"k":100}}]},{"ty":"gr","nm":"Group 6","it":[{"ty":"sh","nm":"Path 1","d":1,"ks":{"a":0,"k":{"c":true,"i":[[0,0],[0,0],[0,0],[0,0]],"o":[[0,0],[0,0],[0,0],[0,0]],"v":[[6.375,-9.75],[-9.375,-9.75],[-6.375,9.75],[9.375,9.75]]}}},{"ty":"st","nm":"Stroke 1","lc":1,"lj":2,"ml":4,"o":{"a":0,"k":100},"w":{"a":0,"k":4.108},"c":{"a":0,"k":[0.1294,0.1294,0.1412]}},{"ty":"fl","nm":"Fill 1","c":{"a":0,"k":[0.1294,0.1294,0.1412]},"r":1,"o":{"a":0,"k":100}},{"ty":"tr","a":{"a":0,"k":[0,0]},"s":{"a":0,"k":[100,100]},"p":{"a":0,"k":[18.375,4.5]},"r":{"a":0,"k":0},"sa":{"a":0,"k":0},"o":{"a":0,"k":100}}]},{"ty":"gr","nm":"Group 7","it":[{"ty":"sh","nm":"Path 1","d":1,"ks":{"a":0,"k":{"c":true,"i":[[0,0],[0,0],[0,0],[0,0]],"o":[[0,0],[0,0],[0,0],[0,0]],"v":[[6.375,-9.75],[-9.375,-9.75],[-6.375,9.75],[9.375,9.75]]}}},{"ty":"st","nm":"Stroke 1","lc":1,"lj":2,"ml":4,"o":{"a":0,"k":100},"w":{"a":0,"k":4.108},"c":{"a":0,"k":[0.1294,0.1294,0.1412]}},{"ty":"tr","a":{"a":0,"k":[0,0]},"s":{"a":0,"k":[100,100]},"p":{"a":0,"k":[2.625,4.5]},"r":{"a":0,"k":0},"sa":{"a":0,"k":0},"o":{"a":0,"k":100}}]},{"ty":"gr","nm":"Group 8","it":[{"ty":"sh","nm":"Path 1","d":1,"ks":{"a":0,"k":{"c":true,"i":[[0,0],[0,0],[0,0],[0,0]],"o":[[0,0],[0,0],[0,0],[0,0]],"v":[[6.375,-9.75],[-9.375,-9.75],[-6.375,9.75],[9.375,9.75]]}}},{"ty":"st","nm":"Stroke 1","lc":1,"lj":2,"ml":4,"o":{"a":0,"k":100},"w":{"a":0,"k":4.108},"c":{"a":0,"k":[0.1294,0.1294,0.1412]}},{"ty":"tr","a":{"a":0,"k":[0,0]},"s":{"a":0,"k":[100,100]},"p":{"a":0,"k":[-13.125,4.5]},"r":{"a":0,"k":0},"sa":{"a":0,"k":0},"o":{"a":0,"k":100}}]},{"ty":"gr","nm":"Group 9","it":[{"ty":"sh","nm":"Path 1","d":1,"ks":{"a":0,"k":{"c":true,"i":[[0,0],[0,0],[0,0],[0,0]],"o":[[0,0],[0,0],[0,0],[0,0]],"v":[[6.375,-9.75],[-9.375,-9.75],[-6.375,9.75],[9.375,9.75]]}}},{"ty":"st","nm":"Stroke 1","lc":1,"lj":2,"ml":4,"o":{"a":0,"k":100},"w":{"a":0,"k":4.108},"c":{"a":0,"k":[0.1294,0.1294,0.1412]}},{"ty":"tr","a":{"a":0,"k":[0,0]},"s":{"a":0,"k":[100,100]},"p":{"a":0,"k":[31.125,-15]},"r":{"a":0,"k":0},"sa":{"a":0,"k":0},"o":{"a":0,"k":100}}]},{"ty":"gr","nm":"Group 10","it":[{"ty":"sh","nm":"Path 1","d":1,"ks":{"a":0,"k":{"c":true,"i":[[0,0],[0,0],[0,0],[0,0]],"o":[[0,0],[0,0],[0,0],[0,0]],"v":[[6.375,-9.75],[-9.375,-9.75],[-6.375,9.75],[9.375,9.75]]}}},{"ty":"st","nm":"Stroke 1","lc":1,"lj":2,"ml":4,"o":{"a":0,"k":100},"w":{"a":0,"k":4.108},"c":{"a":0,"k":[0.1294,0.1294,0.1412]}},{"ty":"tr","a":{"a":0,"k":[0,0]},"s":{"a":0,"k":[100,100]},"p":{"a":0,"k":[15.375,-15]},"r":{"a":0,"k":0},"sa":{"a":0,"k":0},"o":{"a":0,"k":100}}]},{"ty":"gr","nm":"Group 11","it":[{"ty":"sh","nm":"Path 1","d":1,"ks":{"a":0,"k":{"c":true,"i":[[0,0],[0,0],[0,0],[0,0]],"o":[[0,0],[0,0],[0,0],[0,0]],"v":[[6.375,-9.75],[-9.375,-9.75],[-6.375,9.75],[9.375,9.75]]}}},{"ty":"st","nm":"Stroke 1","lc":1,"lj":2,"ml":4,"o":{"a":0,"k":100},"w":{"a":0,"k":4.108},"c":{"a":0,"k":[0.1294,0.1294,0.1412]}},{"ty":"tr","a":{"a":0,"k":[0,0]},"s":{"a":0,"k":[100,100]},"p":{"a":0,"k":[-0.375,-15]},"r":{"a":0,"k":0},"sa":{"a":0,"k":0},"o":{"a":0,"k":100}}]},{"ty":"gr","nm":"Group 12","it":[{"ty":"sh","nm":"Path 1","d":1,"ks":{"a":0,"k":{"c":true,"i":[[0,0],[0,0],[0,0],[0,0]],"o":[[0,0],[0,0],[0,0],[0,0]],"v":[[6.375,-9.75],[-9.375,-9.75],[-6.375,9.75],[9.375,9.75]]}}},{"ty":"st","nm":"Stroke 1","lc":1,"lj":2,"ml":4,"o":{"a":0,"k":100},"w":{"a":0,"k":4.108},"c":{"a":0,"k":[0.1294,0.1294,0.1412]}},{"ty":"tr","a":{"a":0,"k":[0,0]},"s":{"a":0,"k":[100,100]},"p":{"a":0,"k":[-16.125,-15]},"r":{"a":0,"k":0},"sa":{"a":0,"k":0},"o":{"a":0,"k":100}}]},{"ty":"tr","a":{"a":0,"k":[0,0]},"s":{"a":0,"k":[100,100]},"p":{"a":0,"k":[0,0]},"r":{"a":0,"k":0},"sa":{"a":0,"k":0},"o":{"a":0,"k":100}}]},{"ty":"gr","nm":"Partners","it":[{"ty":"sh","nm":"Path 1","d":1,"ks":{"a":0,"k":{"c":false,"i":[[0,0],[0,0]],"o":[[0,0],[0,0]],"v":[[0,-9],[0,9]]}}},{"ty":"st","nm":"Stroke 1","lc":1,"lj":2,"ml":4,"o":{"a":0,"k":100},"w":{"a":0,"k":4.108},"c":{"a":0,"k":[0.1294,0.1294,0.1412]}},{"ty":"tr","a":{"a":0,"k":[0,0]},"s":{"a":0,"k":[100,100]},"p":{"a":0,"k":[36,-45]},"r":{"a":0,"k":0},"sa":{"a":0,"k":0},"o":{"a":0,"k":100}}]},{"ty":"gr","nm":"Partners","it":[{"ty":"sh","nm":"Path 1","d":1,"ks":{"a":0,"k":{"c":false,"i":[[0,0],[0,0]],"o":[[0,0],[0,0]],"v":[[0,-9],[0,9]]}}},{"ty":"st","nm":"Stroke 1","lc":1,"lj":2,"ml":4,"o":{"a":0,"k":100},"w":{"a":0,"k":4.108},"c":{"a":0,"k":[0.1294,0.1294,0.1412]}},{"ty":"tr","a":{"a":0,"k":[0,0]},"s":{"a":0,"k":[100,100]},"p":{"a":0,"k":[13.449,-45]},"r":{"a":0,"k":0},"sa":{"a":0,"k":0},"o":{"a":0,"k":100}}]},{"ty":"gr","nm":"Partners","it":[{"ty":"sh","nm":"Path 1","d":1,"ks":{"a":0,"k":{"c":false,"i":[[0,0],[0,0]],"o":[[0,0],[0,0]],"v":[[0,-9],[0,9]]}}},{"ty":"st","nm":"Stroke 1","lc":1,"lj":2,"ml":4,"o":{"a":0,"k":100},"w":{"a":0,"k":4.108},"c":{"a":0,"k":[0.1294,0.1294,0.1412]}},{"ty":"tr","a":{"a":0,"k":[0,0]},"s":{"a":0,"k":[100,100]},"p":{"a":0,"k":[-31.5,-45]},"r":{"a":0,"k":0},"sa":{"a":0,"k":0},"o":{"a":0,"k":100}}]},{"ty":"gr","nm":"Partners","it":[{"ty":"sh","nm":"Path 1","d":1,"ks":{"a":0,"k":{"c":false,"i":[[0,0],[0,0]],"o":[[0,0],[0,0]],"v":[[0,-9],[0,9]]}}},{"ty":"st","nm":"Stroke 1","lc":1,"lj":2,"ml":4,"o":{"a":0,"k":100},"w":{"a":0,"k":4.108},"c":{"a":0,"k":[0.1294,0.1294,0.1412]}},{"ty":"tr","a":{"a":0,"k":[0,0]},"s":{"a":0,"k":[100,100]},"p":{"a":0,"k":[-9,-45]},"r":{"a":0,"k":0},"sa":{"a":0,"k":0},"o":{"a":0,"k":100}}]},{"ty":"gr","nm":"Partners","it":[{"ty":"sh","nm":"Path 1","d":1,"ks":{"a":0,"k":{"c":true,"i":[[0,0],[0,0],[0,0],[0,0]],"o":[[0,0],[0,0],[0,0],[0,0]],"v":[[40.5,-49.5],[-54,-49.5],[-40.5,49.5],[54,49.5]]}}},{"ty":"st","nm":"Stroke 1","lc":1,"lj":2,"ml":4,"o":{"a":0,"k":100},"w":{"a":0,"k":4},"c":{"a":0,"k":[0.1294,0.1294,0.1412]}},{"ty":"fl","nm":"Fill 1","c":{"a":0,"k":[1,1,1]},"r":1,"o":{"a":0,"k":100}},{"ty":"tr","a":{"a":0,"k":[0,0]},"s":{"a":0,"k":[100,100]},"p":{"a":0,"k":[9,4.5]},"r":{"a":0,"k":0},"sa":{"a":0,"k":0},"o":{"a":0,"k":100}}]},{"ty":"gr","nm":"Partners","it":[{"ty":"sh","nm":"Path 1","d":1,"ks":{"a":0,"k":{"c":true,"i":[[0,0],[0,0],[0,0]],"o":[[0,0],[0,0],[0,0]],"v":[[15.75,49.5],[2.25,-49.5],[-15.75,49.5]]}}},{"ty":"st","nm":"Stroke 1","lc":1,"lj":2,"ml":4,"o":{"a":0,"k":100},"w":{"a":0,"k":4.108},"c":{"a":0,"k":[0.4706,0.2863,1]}},{"ty":"fl","nm":"Fill 1","c":{"a":0,"k":[0.4706,0.2863,1]},"r":1,"o":{"a":0,"k":100}},{"ty":"tr","a":{"a":0,"k":[0,0]},"s":{"a":0,"k":[100,100]},"p":{"a":0,"k":[-47.25,4.5]},"r":{"a":0,"k":0},"sa":{"a":0,"k":0},"o":{"a":0,"k":100}}]}],"ind":3}],"v":"5.7.0","fr":25,"op":125,"ip":0,"assets":[]}